{
    "20210906_11_Std01_MetA_M2_5e5.csv": {
        "102": {
            "13C": {
                "Average": 0.01482200440708115,
                "StdDev": 0.002698032987960968,
                "StdError": 2.3079508036646684e-05,
                "RelStdError": 0.0015571111303691522,
                "TICVar": 0,
                "TIC*ITVar": 0,
                "TIC*ITMean": 0,
                "ShotNoise": 0.001165978809561995
            },
            "13C-13C": {
                "Average": 0.010669019935325989,
                "StdDev": 0.002339922123118016,
                "StdError": 2.001615683966978e-05,
                "RelStdError": 0.0018761008003551165,
                "TICVar": 0,
                "TIC*ITVar": 0,
                "TIC*ITMean": 0,
                "ShotNoise": 0.0013771923309522755
            },
            "18O": {
                "Average": 0.06839824702054206,
                "StdDev": 0.006045982946868717,
                "StdError": 5.171853444132316e-05,
                "RelStdError": 0.0007561383031613445,
                "TICVar": 0,
                "TIC*ITVar": 0,
                "TIC*ITMean": 0,
                "ShotNoise": 0.0005277064563452396
            },
            "Unsub": {
                "Average": 0.9061107286370517,
                "StdDev": 0.006903219758773683,
                "StdError": 5.905150775112031e-05,
                "RelStdError": 6.517029970492024e-05,
                "TICVar": 0,
                "TIC*ITVar": 0,
                "TIC*ITMean": 0,
                "ShotNoise": 4.6029940219755055e-05
            }
        },
        "104": {
            "13C": {
                "Average": 0.008440153873808351,
                "StdDev": 0.0015627173499421557,
                "StdError": 1.3367793425036862e-05,
                "RelStdError": 0.0015838329045777303,
                "TICVar": 0,
                "TIC*ITVar": 0,
                "TIC*ITMean": 0,
                "ShotNoise": 0.0012025799477379145
            },
            "13C-13C": {
                "Average": 0.011295510080868761,
                "StdDev": 0.0018101413336446043,
                "StdError": 1.5484307139213293e-05,
                "RelStdError": 0.00137083735292655,
                "TICVar": 0,
                "TIC*ITVar": 0,
                "TIC*ITMean": 0,
                "ShotNoise": 0.0010379993904287798
            },
            "34S": {
                "Average": 0.9032564404259594,
                "StdDev": 0.005424699816474388,
                "StdError": 4.640395561113416e-05,
                "RelStdError": 5.137406558568339e-05,
                "TICVar": 0,
                "TIC*ITVar": 0,
                "TIC*ITMean": 0,
                "ShotNoise": 3.6307790716501224e-05
            },
            "Unsub": {
                "Average": 0.07700789561936318,
                "StdDev": 0.004959353614138041,
                "StdError": 4.242329211866833e-05,
                "RelStdError": 0.0005508953566055017,
                "TICVar": 0,
                "TIC*ITVar": 0,
                "TIC*ITMean": 0,
                "ShotNoise": 0.0003840411821616488
            }
        },
        "133": {
            "18O": {
                "Average": 0.07115620705980287,
                "StdDev": 0.005913558638046185,
                "StdError": 5.058575070096318e-05,
                "RelStdError": 0.0007109112864665292,
                "TICVar": 0,
                "TIC*ITVar": 0,
                "TIC*ITMean": 0,
                "ShotNoise": 0.0005159704920276269
            },
            "34S": {
                "Average": 0.9288437929401969,
                "StdDev": 0.00591355863804619,
                "StdError": 5.058575070096323e-05,
                "RelStdError": 5.4460988042819555e-05,
                "TICVar": 0,
                "TIC*ITVar": 0,
                "TIC*ITMean": 0,
                "ShotNoise": 3.952817560641585e-05
            }
        },
        "56": {
            "13C": {
                "Average": 0.022613956730548897,
                "StdDev": 0.0012358362458948508,
                "StdError": 1.0571587781313706e-05,
                "RelStdError": 0.0004674806760832211,
                "TICVar": 0,
                "TIC*ITVar": 0,
                "TIC*ITMean": 0,
                "ShotNoise": 0.0003413214544519006
            },
            "13C-13C": {
                "Average": 0.006687887173137391,
                "StdDev": 0.0007227631252642534,
                "StdError": 6.182658786071718e-06,
                "RelStdError": 0.0009244562035832518,
                "TICVar": 0,
                "TIC*ITVar": 0,
                "TIC*ITMean": 0,
                "ShotNoise": 0.0006328685849892469
            },
            "13C-15N": {
                "Average": 0.001930961009073045,
                "StdDev": 0.00035912811552159474,
                "StdError": 3.072052960564592e-06,
                "RelStdError": 0.0015909451025317837,
                "TICVar": 0,
                "TIC*ITVar": 0,
                "TIC*ITMean": 0,
                "ShotNoise": 0.0011808925527776633
            },
            "15N": {
                "Average": 0.001961772570600073,
                "StdDev": 0.0003573484103737933,
                "StdError": 3.056829010581465e-06,
                "RelStdError": 0.0015581974467338143,
                "TICVar": 0,
                "TIC*ITVar": 0,
                "TIC*ITMean": 0,
                "ShotNoise": 0.0011715969931955133
            },
            "Unsub": {
                "Average": 0.9668054225166357,
                "StdDev": 0.0015291346220963266,
                "StdError": 1.3080520126056152e-05,
                "RelStdError": 1.3529630493804018e-05,
                "TICVar": 0,
                "TIC*ITVar": 0,
                "TIC*ITMean": 0,
                "ShotNoise": 9.619690308313111e-06
            }
        },
        "61": {
            "13C": {
                "Average": 0.015501474760110025,
                "StdDev": 0.001148611350356767,
                "StdError": 9.825089300314617e-06,
                "RelStdError": 0.0006338164240732462,
                "TICVar": 0,
                "TIC*ITVar": 0,
                "TIC*ITMean": 0,
                "ShotNoise": 0.00045036256672551016
            },
            "13C-13C": {
                "Average": 0.0014117334379792463,
                "StdDev": 0.00037164078071558405,
                "StdError": 3.178972467088283e-06,
                "RelStdError": 0.002251822037762781,
                "TICVar": 0,
                "TIC*ITVar": 0,
                "TIC*ITMean": 0,
                "ShotNoise": 0.001504277952098248
            },
            "13C-33S": {
                "Average": 0.002004148553821385,
                "StdDev": 0.000466764875298245,
                "StdError": 3.992653024568342e-06,
                "RelStdError": 0.001992194149957298,
                "TICVar": 0,
                "TIC*ITVar": 0,
                "TIC*ITMean": 0,
                "ShotNoise": 0.0012626072714670832
            },
            "33S": {
                "Average": 0.004980142076706651,
                "StdDev": 0.000641390666798233,
                "StdError": 5.4863819478395515e-06,
                "RelStdError": 0.0011016516925291566,
                "TICVar": 0,
                "TIC*ITVar": 0,
                "TIC*ITMean": 0,
                "ShotNoise": 0.0007989385927089393
            },
            "34S": {
                "Average": 0.8850601667327059,
                "StdDev": 0.002919672111037606,
                "StdError": 2.497453922048784e-05,
                "RelStdError": 2.8217899934062127e-05,
                "TICVar": 0,
                "TIC*ITVar": 0,
                "TIC*ITMean": 0,
                "ShotNoise": 2.0368282708489152e-05
            },
            "Unsub": {
                "Average": 0.09104233443867919,
                "StdDev": 0.0026135008390592825,
                "StdError": 2.2355585396425777e-05,
                "RelStdError": 0.0002455515396684297,
                "TICVar": 0,
                "TIC*ITVar": 0,
                "TIC*ITMean": 0,
                "ShotNoise": 0.00017856082885050272
            }
        },
        "74High": {
            "18O": {
                "Average": 0.026374527404105945,
                "StdDev": 0.005016591859608706,
                "StdError": 4.2912919396110234e-05,
                "RelStdError": 0.0016270592734651092,
                "TICVar": 0,
                "TIC*ITVar": 0,
                "TIC*ITMean": 0,
                "ShotNoise": 0.001221787832927816
            },
            "Unsub": {
                "Average": 0.973625472595897,
                "StdDev": 0.0050165918596086975,
                "StdError": 4.291291939611016e-05,
                "RelStdError": 4.407538689563554e-05,
                "TICVar": 0,
                "TIC*ITVar": 0,
                "TIC*ITMean": 0,
                "ShotNoise": 3.3081646935929514e-05
            }
        },
        "74Low": {
            "13C": {
                "Average": 0.013230665989599323,
                "StdDev": 0.002830460968628588,
                "StdError": 2.421232318669608e-05,
                "RelStdError": 0.001830015450902432,
                "TICVar": 0,
                "TIC*ITVar": 0,
                "TIC*ITMean": 0,
                "ShotNoise": 0.001380061161459172
            },
            "18O": {
                "Average": 0.0642387518386252,
                "StdDev": 0.006604526671506474,
                "StdError": 5.649642798047442e-05,
                "RelStdError": 0.0008794758049222323,
                "TICVar": 0,
                "TIC*ITVar": 0,
                "TIC*ITMean": 0,
                "ShotNoise": 0.0006097802444293124
            },
            "Unsub": {
                "Average": 0.9225305821717718,
                "StdDev": 0.007156398954690351,
                "StdError": 6.121725268935641e-05,
                "RelStdError": 6.635796565707563e-05,
                "TICVar": 0,
                "TIC*ITVar": 0,
                "TIC*ITMean": 0,
                "ShotNoise": 4.630506013160975e-05
            }
        },
        "87": {
            "13C": {
                "Average": 0.010168297707274742,
                "StdDev": 0.0020211621104933735,
                "StdError": 1.7289420618889938e-05,
                "RelStdError": 0.0017003259657238895,
                "TICVar": 0,
                "TIC*ITVar": 0,
                "TIC*ITMean": 0,
                "ShotNoise": 0.0012672947189851665
            },
            "13C-13C": {
                "Average": 0.010203720963936874,
                "StdDev": 0.0020227014410624054,
                "StdError": 1.7302588357163544e-05,
                "RelStdError": 0.0016957135949048662,
                "TICVar": 0,
                "TIC*ITVar": 0,
                "TIC*ITMean": 0,
                "ShotNoise": 0.0012651241701117223
            },
            "34S": {
                "Average": 0.9087835508939983,
                "StdDev": 0.0063985551024212306,
                "StdError": 5.4734506423089676e-05,
                "RelStdError": 6.022831989998681e-05,
                "TICVar": 0,
                "TIC*ITVar": 0,
                "TIC*ITMean": 0,
                "ShotNoise": 4.069407394006239e-05
            },
            "Unsub": {
                "Average": 0.07084443043479427,
                "StdDev": 0.005800930499594678,
                "StdError": 4.962230731900936e-05,
                "RelStdError": 0.0007004404864921893,
                "TICVar": 0,
                "TIC*ITVar": 0,
                "TIC*ITMean": 0,
                "ShotNoise": 0.00046504671709771784
            }
        }
    },
    "20210906_13_Smp01_MetMethyl_M2_5e5.csv": {
        "102": {
            "13C": {
                "Average": 0.015612082980471391,
                "StdDev": 0.002772236077357948,
                "StdError": 2.371078615931948e-05,
                "RelStdError": 0.0015187458450597832,
                "TICVar": 0,
                "TIC*ITVar": 0,
                "TIC*ITMean": 0,
                "ShotNoise": 0.0011353633799193095
            },
            "13C-13C": {
                "Average": 0.010669867852264625,
                "StdDev": 0.0023535944710958113,
                "StdError": 2.013016700334351e-05,
                "RelStdError": 0.0018866369557773842,
                "TICVar": 0,
                "TIC*ITVar": 0,
                "TIC*ITMean": 0,
                "ShotNoise": 0.0013765454283184986
            },
            "18O": {
                "Average": 0.06825363384332359,
                "StdDev": 0.005946746491783122,
                "StdError": 5.086220310094713e-05,
                "RelStdError": 0.000745194068607416,
                "TICVar": 0,
                "TIC*ITVar": 0,
                "TIC*ITMean": 0,
                "ShotNoise": 0.0005281368613617946
            },
            "Unsub": {
                "Average": 0.9054644153239414,
                "StdDev": 0.006854422877970484,
                "StdError": 5.8625510443539496e-05,
                "RelStdError": 6.474634392182654e-05,
                "TICVar": 0,
                "TIC*ITVar": 0,
                "TIC*ITMean": 0,
                "ShotNoise": 4.6187994626499824e-05
            }
        },
        "104": {
            "13C": {
                "Average": 0.00868791734216772,
                "StdDev": 0.0015774926188570422,
                "StdError": 1.3492703101492875e-05,
                "RelStdError": 0.0015530422965702752,
                "TICVar": 0,
                "TIC*ITVar": 0,
                "TIC*ITMean": 0,
                "ShotNoise": 0.0011857603445816693
            },
            "13C-13C": {
                "Average": 0.011900742938558292,
                "StdDev": 0.0018788788655472138,
                "StdError": 1.607053775938822e-05,
                "RelStdError": 0.0013503810511963782,
                "TICVar": 0,
                "TIC*ITVar": 0,
                "TIC*ITMean": 0,
                "ShotNoise": 0.0010115351199797686
            },
            "34S": {
                "Average": 0.9024025829154945,
                "StdDev": 0.005431099127470786,
                "StdError": 4.6453598049057634e-05,
                "RelStdError": 5.1477687374270054e-05,
                "TICVar": 0,
                "TIC*ITVar": 0,
                "TIC*ITMean": 0,
                "ShotNoise": 3.6503853248371215e-05
            },
            "Unsub": {
                "Average": 0.07700875680378054,
                "StdDev": 0.004936442403341764,
                "StdError": 4.222267092074832e-05,
                "RelStdError": 0.0005482840221448103,
                "TICVar": 0,
                "TIC*ITVar": 0,
                "TIC*ITMean": 0,
                "ShotNoise": 0.0003842273269387797
            }
        },
        "133": {
            "18O": {
                "Average": 0.07108392618676208,
                "StdDev": 0.005981838137353468,
                "StdError": 5.116421149848297e-05,
                "RelStdError": 0.0007197718843505756,
                "TICVar": 0,
                "TIC*ITVar": 0,
                "TIC*ITMean": 0,
                "ShotNoise": 0.000517234579589763
            },
            "34S": {
                "Average": 0.9289160738132382,
                "StdDev": 0.00598183813735347,
                "StdError": 5.116421149848299e-05,
                "RelStdError": 5.507947697411654e-05,
                "TICVar": 0,
                "TIC*ITVar": 0,
                "TIC*ITMean": 0,
                "ShotNoise": 3.957976644463989e-05
            }
        },
        "56": {
            "13C": {
                "Average": 0.023412711985262194,
                "StdDev": 0.0012657817905759137,
                "StdError": 1.0826559622124341e-05,
                "RelStdError": 0.00046242227850150087,
                "TICVar": 0,
                "TIC*ITVar": 0,
                "TIC*ITMean": 0,
                "ShotNoise": 0.00033555397360549217
            },
            "13C-13C": {
                "Average": 0.006654035376646953,
                "StdDev": 0.0007204038110383693,
                "StdError": 6.161800454297764e-06,
                "RelStdError": 0.0009260246009396432,
                "TICVar": 0,
                "TIC*ITVar": 0,
                "TIC*ITMean": 0,
                "ShotNoise": 0.0006349251434922261
            },
            "13C-15N": {
                "Average": 0.0019259278571436983,
                "StdDev": 0.0003588127112866192,
                "StdError": 3.069018088933939e-06,
                "RelStdError": 0.0015935270251947718,
                "TICVar": 0,
                "TIC*ITVar": 0,
                "TIC*ITMean": 0,
                "ShotNoise": 0.0011833966305601154
            },
            "15N": {
                "Average": 0.0020286856425129735,
                "StdDev": 0.0003565116052508028,
                "StdError": 3.0493361327870892e-06,
                "RelStdError": 0.0015031092392460645,
                "TICVar": 0,
                "TIC*ITVar": 0,
                "TIC*ITMean": 0,
                "ShotNoise": 0.0011528000243404384
            },
            "Unsub": {
                "Average": 0.9659786391384317,
                "StdDev": 0.001546929961498635,
                "StdError": 1.3231292774243025e-05,
                "RelStdError": 1.3697293333571205e-05,
                "TICVar": 0,
                "TIC*ITVar": 0,
                "TIC*ITMean": 0,
                "ShotNoise": 9.749957288510768e-06
            }
        },
        "61": {
            "13C": {
                "Average": 0.01634837883823523,
                "StdDev": 0.0011649084000067563,
                "StdError": 9.963763376030517e-06,
                "RelStdError": 0.0006094649184864425,
                "TICVar": 0,
                "TIC*ITVar": 0,
                "TIC*ITMean": 0,
                "ShotNoise": 0.000438728555031936
            },
            "13C-13C": {
                "Average": 0.0015657776801112882,
                "StdDev": 0.00038959251940417496,
                "StdError": 3.3322857628911105e-06,
                "RelStdError": 0.002128198533686,
                "TICVar": 0,
                "TIC*ITVar": 0,
                "TIC*ITMean": 0,
                "ShotNoise": 0.0014295606570291655
            },
            "13C-33S": {
                "Average": 0.0021149751123123233,
                "StdDev": 0.0004800954070673707,
                "StdError": 4.106380410606178e-06,
                "RelStdError": 0.0019415738685060137,
                "TICVar": 0,
                "TIC*ITVar": 0,
                "TIC*ITMean": 0,
                "ShotNoise": 0.0012301197605105434
            },
            "33S": {
                "Average": 0.004955683632269872,
                "StdDev": 0.0006416787682377649,
                "StdError": 5.488444765362439e-06,
                "RelStdError": 0.0011075050734924627,
                "TICVar": 0,
                "TIC*ITVar": 0,
                "TIC*ITMean": 0,
                "ShotNoise": 0.0008016576088766786
            },
            "34S": {
                "Average": 0.8840850255120738,
                "StdDev": 0.002946242450955403,
                "StdError": 2.5199975062043995e-05,
                "RelStdError": 2.8504017526422683e-05,
                "TICVar": 0,
                "TIC*ITVar": 0,
                "TIC*ITMean": 0,
                "ShotNoise": 2.0483089894298738e-05
            },
            "Unsub": {
                "Average": 0.09093015922499795,
                "StdDev": 0.0026102148762028863,
                "StdError": 2.2325844149573912e-05,
                "RelStdError": 0.00024552738431185144,
                "TICVar": 0,
                "TIC*ITVar": 0,
                "TIC*ITMean": 0,
                "ShotNoise": 0.00017883573900944917
            }
        },
        "74High": {
            "18O": {
                "Average": 0.026320316480318844,
                "StdDev": 0.005013513773722936,
                "StdError": 4.288188232100946e-05,
                "RelStdError": 0.0016292312576512754,
                "TICVar": 0,
                "TIC*ITVar": 0,
                "TIC*ITMean": 0,
                "ShotNoise": 0.0012230203740446334
            },
            "Unsub": {
                "Average": 0.9736796835196817,
                "StdDev": 0.00501351377372294,
                "StdError": 4.2881882321009486e-05,
                "RelStdError": 4.404105687611657e-05,
                "TICVar": 0,
                "TIC*ITVar": 0,
                "TIC*ITMean": 0,
                "ShotNoise": 3.304959940157152e-05
            }
        },
        "74Low": {
            "13C": {
                "Average": 0.013563973237856778,
                "StdDev": 0.002872267092550995,
                "StdError": 2.4567244654404822e-05,
                "RelStdError": 0.0018112129995831998,
                "TICVar": 0,
                "TIC*ITVar": 0,
                "TIC*ITMean": 0,
                "ShotNoise": 0.0013630263089246888
            },
            "18O": {
                "Average": 0.0641498877476531,
                "StdDev": 0.006621754848936309,
                "StdError": 5.6637584936722424e-05,
                "RelStdError": 0.0008828945291302477,
                "TICVar": 0,
                "TIC*ITVar": 0,
                "TIC*ITMean": 0,
                "ShotNoise": 0.0006103637573012312
            },
            "Unsub": {
                "Average": 0.9222861390144877,
                "StdDev": 0.007131534188021448,
                "StdError": 6.099785970905997e-05,
                "RelStdError": 6.613767368795053e-05,
                "TICVar": 0,
                "TIC*ITVar": 0,
                "TIC*ITMean": 0,
                "ShotNoise": 4.639114845208171e-05
            }
        },
        "87": {
            "13C": {
                "Average": 0.010446350189658745,
                "StdDev": 0.0020508579873403194,
                "StdError": 1.7541519748318938e-05,
                "RelStdError": 0.001679200814623655,
                "TICVar": 0,
                "TIC*ITVar": 0,
                "TIC*ITMean": 0,
                "ShotNoise": 0.0012506709204778692
            },
            "13C-13C": {
                "Average": 0.01077211125906593,
                "StdDev": 0.0020852548251817696,
                "StdError": 1.7835724814686312e-05,
                "RelStdError": 0.0016557315818359717,
                "TICVar": 0,
                "TIC*ITVar": 0,
                "TIC*ITMean": 0,
                "ShotNoise": 0.0012312925725607732
            },
            "34S": {
                "Average": 0.9078128457548001,
                "StdDev": 0.00642986095736658,
                "StdError": 5.4996266761924006e-05,
                "RelStdError": 6.058106251646771e-05,
                "TICVar": 0,
                "TIC*ITVar": 0,
                "TIC*ITMean": 0,
                "ShotNoise": 4.094232410010561e-05
            },
            "Unsub": {
                "Average": 0.07096869279647096,
                "StdDev": 0.005777572406556266,
                "StdError": 4.941707377719651e-05,
                "RelStdError": 0.0006963221644636782,
                "TICVar": 0,
                "TIC*ITVar": 0,
                "TIC*ITMean": 0,
                "ShotNoise": 0.00046475847140362876
            }
        }
    },
    "20210906_15_Std02_MetA_M2_5e5.csv": {
        "102": {
            "13C": {
                "Average": 0.014825923869259097,
                "StdDev": 0.0026928352899717014,
                "StdError": 2.3035045899582155e-05,
                "RelStdError": 0.001553700538510407,
                "TICVar": 0,
                "TIC*ITVar": 0,
                "TIC*ITMean": 0,
                "ShotNoise": 0.0011685070837056193
            },
            "13C-13C": {
                "Average": 0.010638749522832884,
                "StdDev": 0.002371914892127654,
                "StdError": 2.028982931616183e-05,
                "RelStdError": 0.001907162986835605,
                "TICVar": 0,
                "TIC*ITVar": 0,
                "TIC*ITMean": 0,
                "ShotNoise": 0.0013823379150608708
            },
            "18O": {
                "Average": 0.06845894455524064,
                "StdDev": 0.006041503358001835,
                "StdError": 5.168021515178318e-05,
                "RelStdError": 0.0007549081495126115,
                "TICVar": 0,
                "TIC*ITVar": 0,
                "TIC*ITMean": 0,
                "ShotNoise": 0.0005286500420737262
            },
            "Unsub": {
                "Average": 0.9060763820526699,
                "StdDev": 0.006914923787419507,
                "StdError": 5.915162632802347e-05,
                "RelStdError": 6.52832669515328e-05,
                "TICVar": 0,
                "TIC*ITVar": 0,
                "TIC*ITMean": 0,
                "ShotNoise": 4.614268025193318e-05
            }
        },
        "104": {
            "13C": {
                "Average": 0.008472597982801987,
                "StdDev": 0.0015695835316763694,
                "StdError": 1.342701936756399e-05,
                "RelStdError": 0.001584758228210365,
                "TICVar": 0,
                "TIC*ITVar": 0,
                "TIC*ITMean": 0,
                "ShotNoise": 0.001202565002589939
            },
            "13C-13C": {
                "Average": 0.011343597137946474,
                "StdDev": 0.0018374702590565715,
                "StdError": 1.5718659286215323e-05,
                "RelStdError": 0.0013856856070490586,
                "TICVar": 0,
                "TIC*ITVar": 0,
                "TIC*ITMean": 0,
                "ShotNoise": 0.001037722959911981
            },
            "34S": {
                "Average": 0.9031130026484473,
                "StdDev": 0.005463957873764009,
                "StdError": 4.674148697025835e-05,
                "RelStdError": 5.17559672302197e-05,
                "TICVar": 0,
                "TIC*ITVar": 0,
                "TIC*ITMean": 0,
                "ShotNoise": 3.640645746798667e-05
            },
            "Unsub": {
                "Average": 0.07707080223080402,
                "StdDev": 0.004990769096219235,
                "StdError": 4.269358843387282e-05,
                "RelStdError": 0.0005539528225749912,
                "TICVar": 0,
                "TIC*ITVar": 0,
                "TIC*ITMean": 0,
                "ShotNoise": 0.00038456160838850137
            }
        },
        "133": {
            "18O": {
                "Average": 0.07109912450639443,
                "StdDev": 0.005936555184436596,
                "StdError": 5.078432579686237e-05,
                "RelStdError": 0.0007142749808725843,
                "TICVar": 0,
                "TIC*ITVar": 0,
                "TIC*ITMean": 0,
                "ShotNoise": 0.0005180071455021138
            },
            "34S": {
                "Average": 0.9289008754936051,
                "StdDev": 0.005936555184436581,
                "StdError": 5.078432579686224e-05,
                "RelStdError": 5.467141558013512e-05,
                "TICVar": 0,
                "TIC*ITVar": 0,
                "TIC*ITMean": 0,
                "ShotNoise": 3.964702292778603e-05
            }
        },
        "56": {
            "13C": {
                "Average": 0.022563997752947713,
                "StdDev": 0.0012441592090607066,
                "StdError": 1.064317346560671e-05,
                "RelStdError": 0.0004716882877820845,
                "TICVar": 0,
                "TIC*ITVar": 0,
                "TIC*ITMean": 0,
                "ShotNoise": 0.0003421989003569099
            },
            "13C-13C": {
                "Average": 0.006641534215762154,
                "StdDev": 0.0007197884319555114,
                "StdError": 6.157437958139779e-06,
                "RelStdError": 0.0009271107786400491,
                "TICVar": 0,
                "TIC*ITVar": 0,
                "TIC*ITMean": 0,
                "ShotNoise": 0.000636000561357327
            },
            "13C-15N": {
                "Average": 0.0019181682435318469,
                "StdDev": 0.0003560721655309189,
                "StdError": 3.046023207014563e-06,
                "RelStdError": 0.0015879854216573005,
                "TICVar": 0,
                "TIC*ITVar": 0,
                "TIC*ITMean": 0,
                "ShotNoise": 0.0011866462456556902
            },
            "15N": {
                "Average": 0.001954515899670025,
                "StdDev": 0.0003532626017092156,
                "StdError": 3.021988762789651e-06,
                "RelStdError": 0.0015461571652089624,
                "TICVar": 0,
                "TIC*ITVar": 0,
                "TIC*ITMean": 0,
                "ShotNoise": 0.0011753760838778722
            },
            "Unsub": {
                "Average": 0.9669217838880856,
                "StdDev": 0.0015440785168263959,
                "StdError": 1.3208836441042808e-05,
                "RelStdError": 1.366070830251523e-05,
                "TICVar": 0,
                "TIC*ITVar": 0,
                "TIC*ITMean": 0,
                "ShotNoise": 9.616145409902343e-06
            }
        },
        "61": {
            "13C": {
                "Average": 0.015494829789800357,
                "StdDev": 0.0011452390854630355,
                "StdError": 9.795526632367913e-06,
                "RelStdError": 0.0006321803314558464,
                "TICVar": 0,
                "TIC*ITVar": 0,
                "TIC*ITMean": 0,
                "ShotNoise": 0.00045097265035075725
            },
            "13C-13C": {
                "Average": 0.0014048214185483114,
                "StdDev": 0.00037423288213458565,
                "StdError": 3.200910805602658e-06,
                "RelStdError": 0.0022785179406720297,
                "TICVar": 0,
                "TIC*ITVar": 0,
                "TIC*ITMean": 0,
                "ShotNoise": 0.0015098322529878319
            },
            "13C-33S": {
                "Average": 0.002009150681842567,
                "StdDev": 0.00047633258680792614,
                "StdError": 4.074196033970709e-06,
                "RelStdError": 0.0020278200489344655,
                "TICVar": 0,
                "TIC*ITVar": 0,
                "TIC*ITMean": 0,
                "ShotNoise": 0.0012624530577739067
            },
            "33S": {
                "Average": 0.004959893752867933,
                "StdDev": 0.0006501010883584986,
                "StdError": 5.5604830515999534e-06,
                "RelStdError": 0.001121089145989215,
                "TICVar": 0,
                "TIC*ITVar": 0,
                "TIC*ITMean": 0,
                "ShotNoise": 0.0008015131708336604
            },
            "34S": {
                "Average": 0.8851260008620646,
                "StdDev": 0.002917448191142448,
                "StdError": 2.495369029719676e-05,
                "RelStdError": 2.8192246384009986e-05,
                "TICVar": 0,
                "TIC*ITVar": 0,
                "TIC*ITMean": 0,
                "ShotNoise": 2.038522921630386e-05
            },
            "Unsub": {
                "Average": 0.09100530349487702,
                "StdDev": 0.002615480033969811,
                "StdError": 2.2370878408170384e-05,
                "RelStdError": 0.00024581950226043375,
                "TICVar": 0,
                "TIC*ITVar": 0,
                "TIC*ITMean": 0,
                "ShotNoise": 0.00017880233586325562
            }
        },
        "74High": {
            "18O": {
                "Average": 0.02642416013458915,
                "StdDev": 0.005036104480133996,
                "StdError": 4.3081410467918576e-05,
                "RelStdError": 0.0016303795560005379,
                "TICVar": 0,
                "TIC*ITVar": 0,
                "TIC*ITMean": 0,
                "ShotNoise": 0.0012227377975630508
            },
            "Unsub": {
                "Average": 0.9735758398654095,
                "StdDev": 0.0050361044801340085,
                "StdError": 4.308141046791868e-05,
                "RelStdError": 4.4250697997882114e-05,
                "TICVar": 0,
                "TIC*ITVar": 0,
                "TIC*ITMean": 0,
                "ShotNoise": 3.3167562800001e-05
            }
        },
        "74Low": {
            "13C": {
                "Average": 0.013135283962012337,
                "StdDev": 0.0028835523803249184,
                "StdError": 2.466738015316476e-05,
                "RelStdError": 0.0018779479929405115,
                "TICVar": 0,
                "TIC*ITVar": 0,
                "TIC*ITMean": 0,
                "ShotNoise": 0.0013863115238296404
            },
            "18O": {
                "Average": 0.0641908839169999,
                "StdDev": 0.006625171724150133,
                "StdError": 5.6675103464288225e-05,
                "RelStdError": 0.0008829151431778113,
                "TICVar": 0,
                "TIC*ITVar": 0,
                "TIC*ITMean": 0,
                "ShotNoise": 0.0006104694906951646
            },
            "Unsub": {
                "Average": 0.9226738321209877,
                "StdDev": 0.007157553627243958,
                "StdError": 6.122937023602654e-05,
                "RelStdError": 6.636079631225273e-05,
                "TICVar": 0,
                "TIC*ITVar": 0,
                "TIC*ITMean": 0,
                "ShotNoise": 4.62910176363808e-05
            }
        },
        "87": {
            "13C": {
                "Average": 0.010200186606517517,
                "StdDev": 0.0020353021439988087,
                "StdError": 1.7411014294428298e-05,
                "RelStdError": 0.001706930957841825,
                "TICVar": 0,
                "TIC*ITVar": 0,
                "TIC*ITMean": 0,
                "ShotNoise": 0.0012667843318533197
            },
            "13C-13C": {
                "Average": 0.010218878143460555,
                "StdDev": 0.0020382276541858094,
                "StdError": 1.7436040603094336e-05,
                "RelStdError": 0.0017062578062203742,
                "TICVar": 0,
                "TIC*ITVar": 0,
                "TIC*ITMean": 0,
                "ShotNoise": 0.0012656014870156176
            },
            "34S": {
                "Average": 0.9086178893931264,
                "StdDev": 0.00628341935151378,
                "StdError": 5.375157908110465e-05,
                "RelStdError": 5.915751792759197e-05,
                "TICVar": 0,
                "TIC*ITVar": 0,
                "TIC*ITMean": 0,
                "ShotNoise": 4.077537029048609e-05
            },
            "Unsub": {
                "Average": 0.07096304585689214,
                "StdDev": 0.005708492321421282,
                "StdError": 4.883335955841173e-05,
                "RelStdError": 0.0006881519665445545,
                "TICVar": 0,
                "TIC*ITVar": 0,
                "TIC*ITMean": 0,
                "ShotNoise": 0.00046513130587146393
            }
        }
    },
    "20210906_17_Smp02_MetMethyl_M2_5e5.csv": {
        "102": {
            "13C": {
                "Average": 0.0160308337235619,
                "StdDev": 0.002786572008427904,
                "StdError": 2.384125015291686e-05,
                "RelStdError": 0.0014872121166022273,
                "TICVar": 0,
                "TIC*ITVar": 0,
                "TIC*ITMean": 0,
                "ShotNoise": 0.001123616190406482
            },
            "13C-13C": {
                "Average": 0.010620802441946305,
                "StdDev": 0.00234509114634569,
                "StdError": 2.006404445401745e-05,
                "RelStdError": 0.001889126981100369,
                "TICVar": 0,
                "TIC*ITVar": 0,
                "TIC*ITMean": 0,
                "ShotNoise": 0.0013841471351669847
            },
            "18O": {
                "Average": 0.06832311917052733,
                "StdDev": 0.005959797060539359,
                "StdError": 5.0990612175530894e-05,
                "RelStdError": 0.0007463156365602057,
                "TICVar": 0,
                "TIC*ITVar": 0,
                "TIC*ITMean": 0,
                "ShotNoise": 0.000529460584764147
            },
            "Unsub": {
                "Average": 0.9050252446639642,
                "StdDev": 0.00684453818920205,
                "StdError": 5.856024773679579e-05,
                "RelStdError": 6.470565112085818e-05,
                "TICVar": 0,
                "TIC*ITVar": 0,
                "TIC*ITMean": 0,
                "ShotNoise": 4.644888628221345e-05
            }
        },
        "104": {
            "13C": {
                "Average": 0.00873144622798291,
                "StdDev": 0.0015981193183017737,
                "StdError": 1.3673130400580255e-05,
                "RelStdError": 0.0015659639930851346,
                "TICVar": 0,
                "TIC*ITVar": 0,
                "TIC*ITMean": 0,
                "ShotNoise": 0.0011864092656745295
            },
            "13C-13C": {
                "Average": 0.011898686025384799,
                "StdDev": 0.0018884969400142127,
                "StdError": 1.6157532561054492e-05,
                "RelStdError": 0.0013579257849634673,
                "TICVar": 0,
                "TIC*ITVar": 0,
                "TIC*ITMean": 0,
                "ShotNoise": 0.0010146395348451314
            },
            "34S": {
                "Average": 0.9024265694146788,
                "StdDev": 0.005495077114027061,
                "StdError": 4.701457837402129e-05,
                "RelStdError": 5.20979545233418e-05,
                "TICVar": 0,
                "TIC*ITVar": 0,
                "TIC*ITMean": 0,
                "ShotNoise": 3.661109162837169e-05
            },
            "Unsub": {
                "Average": 0.0769432983319529,
                "StdDev": 0.004980775119988297,
                "StdError": 4.261433231652222e-05,
                "RelStdError": 0.0005538407273973776,
                "TICVar": 0,
                "TIC*ITVar": 0,
                "TIC*ITMean": 0,
                "ShotNoise": 0.0003855728734013444
            }
        },
        "133": {
            "18O": {
                "Average": 0.07108615144826605,
                "StdDev": 0.005942824536432033,
                "StdError": 5.0845399278916216e-05,
                "RelStdError": 0.0007152644818016301,
                "TICVar": 0,
                "TIC*ITVar": 0,
                "TIC*ITMean": 0,
                "ShotNoise": 0.0005190055957591842
            },
            "34S": {
                "Average": 0.9289138485517348,
                "StdDev": 0.005942824536432045,
                "StdError": 5.084539927891632e-05,
                "RelStdError": 5.473639924540811e-05,
                "TICVar": 0,
                "TIC*ITVar": 0,
                "TIC*ITMean": 0,
                "ShotNoise": 3.971333985366806e-05
            }
        },
        "56": {
            "13C": {
                "Average": 0.023819824926069603,
                "StdDev": 0.0012792843339536216,
                "StdError": 1.0945253785027042e-05,
                "RelStdError": 0.00045950185691952803,
                "TICVar": 0,
                "TIC*ITVar": 0,
                "TIC*ITMean": 0,
                "ShotNoise": 0.0003327694345777657
            },
            "13C-13C": {
                "Average": 0.006626657977409322,
                "StdDev": 0.0007243649804851169,
                "StdError": 6.197495219763393e-06,
                "RelStdError": 0.0009352369234825502,
                "TICVar": 0,
                "TIC*ITVar": 0,
                "TIC*ITMean": 0,
                "ShotNoise": 0.0006365678864091476
            },
            "13C-15N": {
                "Average": 0.0019033871268884187,
                "StdDev": 0.00035967104541374573,
                "StdError": 3.077260282718472e-06,
                "RelStdError": 0.0016167285358018862,
                "TICVar": 0,
                "TIC*ITVar": 0,
                "TIC*ITMean": 0,
                "ShotNoise": 0.0011908813851847478
            },
            "15N": {
                "Average": 0.00206240811716449,
                "StdDev": 0.00036107193959181557,
                "StdError": 3.0892460015285777e-06,
                "RelStdError": 0.0014978829727337576,
                "TICVar": 0,
                "TIC*ITVar": 0,
                "TIC*ITMean": 0,
                "ShotNoise": 0.0011439782298868057
            },
            "Unsub": {
                "Average": 0.9655877218524638,
                "StdDev": 0.001561896843440557,
                "StdError": 1.3363219484331863e-05,
                "RelStdError": 1.3839467074720827e-05,
                "TICVar": 0,
                "TIC*ITVar": 0,
                "TIC*ITMean": 0,
                "ShotNoise": 9.81303369107168e-06
            }
        },
        "61": {
            "13C": {
                "Average": 0.01632522133122974,
                "StdDev": 0.0011673308778998408,
                "StdError": 9.987406529262925e-06,
                "RelStdError": 0.000611777710490042,
                "TICVar": 0,
                "TIC*ITVar": 0,
                "TIC*ITMean": 0,
                "ShotNoise": 0.00043925799968126645
            },
            "13C-13C": {
                "Average": 0.0015685067341503092,
                "StdDev": 0.00038770913582431845,
                "StdError": 3.317147543936491e-06,
                "RelStdError": 0.002114844311289141,
                "TICVar": 0,
                "TIC*ITVar": 0,
                "TIC*ITMean": 0,
                "ShotNoise": 0.0014292984186259163
            },
            "13C-33S": {
                "Average": 0.0021229067356917037,
                "StdDev": 0.00047873203711983585,
                "StdError": 4.095917930227348e-06,
                "RelStdError": 0.0019293913676771963,
                "TICVar": 0,
                "TIC*ITVar": 0,
                "TIC*ITMean": 0,
                "ShotNoise": 0.0012283406884156605
            },
            "33S": {
                "Average": 0.0049499481267382935,
                "StdDev": 0.0006454166562503014,
                "StdError": 5.522032055149994e-06,
                "RelStdError": 0.0011155737219389142,
                "TICVar": 0,
                "TIC*ITVar": 0,
                "TIC*ITMean": 0,
                "ShotNoise": 0.0008025346620400909
            },
            "34S": {
                "Average": 0.8841357364464786,
                "StdDev": 0.0029540202167497665,
                "StdError": 2.527389736611826e-05,
                "RelStdError": 2.858599231346444e-05,
                "TICVar": 0,
                "TIC*ITVar": 0,
                "TIC*ITMean": 0,
                "ShotNoise": 2.048913997613501e-05
            },
            "Unsub": {
                "Average": 0.09089768062571128,
                "StdDev": 0.0026189770091447646,
                "StdError": 2.2407347031015667e-05,
                "RelStdError": 0.00024651175780031435,
                "TICVar": 0,
                "TIC*ITVar": 0,
                "TIC*ITMean": 0,
                "ShotNoise": 0.00017896543129020023
            }
        },
        "74High": {
            "18O": {
                "Average": 0.026321367717261818,
                "StdDev": 0.005029672010522319,
                "StdError": 4.303268253155188e-05,
                "RelStdError": 0.0016348953821016911,
                "TICVar": 0,
                "TIC*ITVar": 0,
                "TIC*ITMean": 0,
                "ShotNoise": 0.0012257842447482398
            },
            "Unsub": {
                "Average": 0.9736786322827415,
                "StdDev": 0.005029672010522323,
                "StdError": 4.303268253155191e-05,
                "RelStdError": 4.419598120445953e-05,
                "TICVar": 0,
                "TIC*ITVar": 0,
                "TIC*ITMean": 0,
                "ShotNoise": 3.312804915285623e-05
            }
        },
        "74Low": {
            "13C": {
                "Average": 0.013716212938666605,
                "StdDev": 0.0029223371920939546,
                "StdError": 2.5002824910737356e-05,
                "RelStdError": 0.0018228664881873697,
                "TICVar": 0,
                "TIC*ITVar": 0,
                "TIC*ITMean": 0,
                "ShotNoise": 0.0013565240559317933
            },
            "18O": {
                "Average": 0.06400615440079738,
                "StdDev": 0.006628476079482775,
                "StdError": 5.671167149659651e-05,
                "RelStdError": 0.0008860346638149223,
                "TICVar": 0,
                "TIC*ITVar": 0,
                "TIC*ITMean": 0,
                "ShotNoise": 0.000611544759679775
            },
            "Unsub": {
                "Average": 0.9222776326605359,
                "StdDev": 0.007197321623680615,
                "StdError": 6.157857925156391e-05,
                "RelStdError": 6.676794174648409e-05,
                "TICVar": 0,
                "TIC*ITVar": 0,
                "TIC*ITMean": 0,
                "ShotNoise": 4.64290112759368e-05
            }
        },
        "87": {
            "13C": {
                "Average": 0.010492282687943973,
                "StdDev": 0.0020484102011620476,
                "StdError": 1.7525712550756306e-05,
                "RelStdError": 0.0016703431533439343,
                "TICVar": 0,
                "TIC*ITVar": 0,
                "TIC*ITMean": 0,
                "ShotNoise": 0.0012496052869316676
            },
            "13C-13C": {
                "Average": 0.010771264410885219,
                "StdDev": 0.002067848348629991,
                "StdError": 1.7692020736904336e-05,
                "RelStdError": 0.0016425203264925094,
                "TICVar": 0,
                "TIC*ITVar": 0,
                "TIC*ITMean": 0,
                "ShotNoise": 0.001233104124732854
            },
            "34S": {
                "Average": 0.9078466009626697,
                "StdDev": 0.006376114212923063,
                "StdError": 5.4552523133837534e-05,
                "RelStdError": 6.009002300167307e-05,
                "TICVar": 0,
                "TIC*ITVar": 0,
                "TIC*ITMean": 0,
                "ShotNoise": 4.0993402604281414e-05
            },
            "Unsub": {
                "Average": 0.07088985193849691,
                "StdDev": 0.005748510246270329,
                "StdError": 4.91828922322581e-05,
                "RelStdError": 0.000693793129585438,
                "TICVar": 0,
                "TIC*ITVar": 0,
                "TIC*ITMean": 0,
                "ShotNoise": 0.00046570816482505834
            }
        }
    },
    "20210906_19_Std03_MetA_M2_5e5.csv": {
        "102": {
            "13C": {
                "Average": 0.015227264504144621,
                "StdDev": 0.002730508805929099,
                "StdError": 2.3364152232675683e-05,
                "RelStdError": 0.0015343630647721611,
                "TICVar": 0,
                "TIC*ITVar": 0,
                "TIC*ITMean": 0,
                "ShotNoise": 0.0011543634593528373
            },
            "13C-13C": {
                "Average": 0.010665509868977293,
                "StdDev": 0.0023443431847143584,
                "StdError": 2.005984779626609e-05,
                "RelStdError": 0.0018808147048472623,
                "TICVar": 0,
                "TIC*ITVar": 0,
                "TIC*ITMean": 0,
                "ShotNoise": 0.0013824278199861097
            },
            "18O": {
                "Average": 0.06836262231492225,
                "StdDev": 0.005996130892855357,
                "StdError": 5.130710975314095e-05,
                "RelStdError": 0.0007505140677136018,
                "TICVar": 0,
                "TIC*ITVar": 0,
                "TIC*ITMean": 0,
                "ShotNoise": 0.000529773845703069
            },
            "Unsub": {
                "Average": 0.9057446033119536,
                "StdDev": 0.006857186915207421,
                "StdError": 5.867491019509938e-05,
                "RelStdError": 6.478085542055474e-05,
                "TICVar": 0,
                "TIC*ITVar": 0,
                "TIC*ITMean": 0,
                "ShotNoise": 4.6298052921392735e-05
            }
        },
        "104": {
            "13C": {
                "Average": 0.008494779142797575,
                "StdDev": 0.001576096395979463,
                "StdError": 1.3486188379643647e-05,
                "RelStdError": 0.0015875855219941901,
                "TICVar": 0,
                "TIC*ITVar": 0,
                "TIC*ITMean": 0,
                "ShotNoise": 0.001203003392487076
            },
            "13C-13C": {
                "Average": 0.01131433010526589,
                "StdDev": 0.0018413996347975638,
                "StdError": 1.5756309335162357e-05,
                "RelStdError": 0.0013925976340242265,
                "TICVar": 0,
                "TIC*ITVar": 0,
                "TIC*ITMean": 0,
                "ShotNoise": 0.001040969372890421
            },
            "34S": {
                "Average": 0.903209207133079,
                "StdDev": 0.005482012647905305,
                "StdError": 4.690795274821716e-05,
                "RelStdError": 5.193475927588251e-05,
                "TICVar": 0,
                "TIC*ITVar": 0,
                "TIC*ITMean": 0,
                "ShotNoise": 3.6450978853025726e-05
            },
            "Unsub": {
                "Average": 0.07698168361885828,
                "StdDev": 0.005010253005459879,
                "StdError": 4.287124571420448e-05,
                "RelStdError": 0.0005569018979431916,
                "TICVar": 0,
                "TIC*ITVar": 0,
                "TIC*ITMean": 0,
                "ShotNoise": 0.00038547512664839086
            }
        },
        "133": {
            "18O": {
                "Average": 0.07105002979206229,
                "StdDev": 0.005946483120345526,
                "StdError": 5.088228852113681e-05,
                "RelStdError": 0.0007161473214022688,
                "TICVar": 0,
                "TIC*ITVar": 0,
                "TIC*ITMean": 0,
                "ShotNoise": 0.0005192647949689012
            },
            "34S": {
                "Average": 0.928949970207941,
                "StdDev": 0.00594648312034552,
                "StdError": 5.088228852113676e-05,
                "RelStdError": 5.477398154148927e-05,
                "TICVar": 0,
                "TIC*ITVar": 0,
                "TIC*ITMean": 0,
                "ShotNoise": 3.9713073290226844e-05
            }
        },
        "56": {
            "13C": {
                "Average": 0.02296517568626787,
                "StdDev": 0.001250360103814379,
                "StdError": 1.0698959749826892e-05,
                "RelStdError": 0.00046587754851030305,
                "TICVar": 0,
                "TIC*ITVar": 0,
                "TIC*ITMean": 0,
                "ShotNoise": 0.00033940276484639335
            },
            "13C-13C": {
                "Average": 0.006624512941766296,
                "StdDev": 0.0007142450136400001,
                "StdError": 6.11158227868678e-06,
                "RelStdError": 0.0009225708112296701,
                "TICVar": 0,
                "TIC*ITVar": 0,
                "TIC*ITMean": 0,
                "ShotNoise": 0.0006373058815527685
            },
            "13C-15N": {
                "Average": 0.0019119028033801233,
                "StdDev": 0.0003554286371192849,
                "StdError": 3.0412971998021988e-06,
                "RelStdError": 0.0015907174749811431,
                "TICVar": 0,
                "TIC*ITVar": 0,
                "TIC*ITMean": 0,
                "ShotNoise": 0.001189512059826401
            },
            "15N": {
                "Average": 0.001985010165692368,
                "StdDev": 0.00035440527303717985,
                "StdError": 3.0325405775375736e-06,
                "RelStdError": 0.0015277204268018593,
                "TICVar": 0,
                "TIC*ITVar": 0,
                "TIC*ITMean": 0,
                "ShotNoise": 0.0011672791334972987
            },
            "Unsub": {
                "Average": 0.9665133984028945,
                "StdDev": 0.0015389369099466333,
                "StdError": 1.3168225702990203e-05,
                "RelStdError": 1.3624462655923763e-05,
                "TICVar": 0,
                "TIC*ITVar": 0,
                "TIC*ITMean": 0,
                "ShotNoise": 9.685482173742034e-06
            }
        },
        "61": {
            "13C": {
                "Average": 0.015491110555205077,
                "StdDev": 0.0011485000697570927,
                "StdError": 9.824856319565859e-06,
                "RelStdError": 0.0006342254342936483,
                "TICVar": 0,
                "TIC*ITVar": 0,
                "TIC*ITMean": 0,
                "ShotNoise": 0.0004511682512905499
            },
            "13C-13C": {
                "Average": 0.00141415619436021,
                "StdDev": 0.00037186774455376435,
                "StdError": 3.1811466593071065e-06,
                "RelStdError": 0.0022495016264779118,
                "TICVar": 0,
                "TIC*ITVar": 0,
                "TIC*ITMean": 0,
                "ShotNoise": 0.0015054350208989807
            },
            "13C-33S": {
                "Average": 0.002009438157499291,
                "StdDev": 0.00047822443616456266,
                "StdError": 4.090976132736284e-06,
                "RelStdError": 0.0020358805855600097,
                "TICVar": 0,
                "TIC*ITVar": 0,
                "TIC*ITMean": 0,
                "ShotNoise": 0.001262874448367341
            },
            "33S": {
                "Average": 0.004953305826248598,
                "StdDev": 0.0006408943059460916,
                "StdError": 5.4825373003938794e-06,
                "RelStdError": 0.0011068440941685396,
                "TICVar": 0,
                "TIC*ITVar": 0,
                "TIC*ITMean": 0,
                "ShotNoise": 0.0008023037810984437
            },
            "34S": {
                "Average": 0.8851442203744659,
                "StdDev": 0.002913178829176522,
                "StdError": 2.492081993161208e-05,
                "RelStdError": 2.8154530479868205e-05,
                "TICVar": 0,
                "TIC*ITVar": 0,
                "TIC*ITMean": 0,
                "ShotNoise": 2.0389711835649593e-05
            },
            "Unsub": {
                "Average": 0.0909877688922226,
                "StdDev": 0.002601588441820554,
                "StdError": 2.225531657907182e-05,
                "RelStdError": 0.00024459679416289265,
                "TICVar": 0,
                "TIC*ITVar": 0,
                "TIC*ITMean": 0,
                "ShotNoise": 0.00017888394009330235
            }
        },
        "74High": {
            "18O": {
                "Average": 0.02640703073139902,
                "StdDev": 0.004999668137670657,
                "StdError": 4.27806741467907e-05,
                "RelStdError": 0.0016200486371200666,
                "TICVar": 0,
                "TIC*ITVar": 0,
                "TIC*ITMean": 0,
                "ShotNoise": 0.0012245301213936626
            },
            "Unsub": {
                "Average": 0.9735929692686013,
                "StdDev": 0.004999668137670657,
                "StdError": 4.27806741467907e-05,
                "RelStdError": 4.394102617537297e-05,
                "TICVar": 0,
                "TIC*ITVar": 0,
                "TIC*ITMean": 0,
                "ShotNoise": 3.319924423111041e-05
            }
        },
        "74Low": {
            "13C": {
                "Average": 0.01328543916654284,
                "StdDev": 0.002874372420579053,
                "StdError": 2.459515042104475e-05,
                "RelStdError": 0.0018512862173938164,
                "TICVar": 0,
                "TIC*ITVar": 0,
                "TIC*ITMean": 0,
                "ShotNoise": 0.0013787952325559445
            },
            "18O": {
                "Average": 0.06410806540926356,
                "StdDev": 0.006527413694049742,
                "StdError": 5.585313876383454e-05,
                "RelStdError": 0.000871234195062199,
                "TICVar": 0,
                "TIC*ITVar": 0,
                "TIC*ITMean": 0,
                "ShotNoise": 0.0006111315588939577
            },
            "Unsub": {
                "Average": 0.9226064954241959,
                "StdDev": 0.007082271965126746,
                "StdError": 6.06008960627132e-05,
                "RelStdError": 6.568444549574749e-05,
                "TICVar": 0,
                "TIC*ITVar": 0,
                "TIC*ITMean": 0,
                "ShotNoise": 4.6323585608367534e-05
            }
        },
        "87": {
            "13C": {
                "Average": 0.010235955278831093,
                "StdDev": 0.0020529520391272915,
                "StdError": 1.7566500376925533e-05,
                "RelStdError": 0.0017161564210088616,
                "TICVar": 0,
                "TIC*ITVar": 0,
                "TIC*ITMean": 0,
                "ShotNoise": 0.0012652726065761617
            },
            "13C-13C": {
                "Average": 0.010272563789120026,
                "StdDev": 0.0020520824365395573,
                "StdError": 1.755905944606399e-05,
                "RelStdError": 0.0017093161752532804,
                "TICVar": 0,
                "TIC*ITVar": 0,
                "TIC*ITMean": 0,
                "ShotNoise": 0.0012629544080480983
            },
            "34S": {
                "Average": 0.9086588084735906,
                "StdDev": 0.006387127725629693,
                "StdError": 5.465275343083097e-05,
                "RelStdError": 6.014661710333203e-05,
                "TICVar": 0,
                "TIC*ITVar": 0,
                "TIC*ITMean": 0,
                "ShotNoise": 4.079254272417275e-05
            },
            "Unsub": {
                "Average": 0.0708326724584588,
                "StdDev": 0.005788972894365713,
                "StdError": 4.9534520335953e-05,
                "RelStdError": 0.0006993173999612041,
                "TICVar": 0,
                "TIC*ITVar": 0,
                "TIC*ITMean": 0,
                "ShotNoise": 0.00046582980647928045
            }
        }
    },
    "20210906_21_Smp03_MetMethyl_M2_5e5.csv": {
        "102": {
            "13C": {
                "Average": 0.01606337358957564,
                "StdDev": 0.002801611025778689,
                "StdError": 2.3954144394740835e-05,
                "RelStdError": 0.001491227497210544,
                "TICVar": 0,
                "TIC*ITVar": 0,
                "TIC*ITMean": 0,
                "ShotNoise": 0.0011222495517508569
            },
            "13C-13C": {
                "Average": 0.010638732365726744,
                "StdDev": 0.0023345148508211212,
                "StdError": 1.996041039019435e-05,
                "RelStdError": 0.0018762019481285102,
                "TICVar": 0,
                "TIC*ITVar": 0,
                "TIC*ITMean": 0,
                "ShotNoise": 0.0013826738335267089
            },
            "18O": {
                "Average": 0.0683481172347325,
                "StdDev": 0.006016737475993803,
                "StdError": 5.144390029845248e-05,
                "RelStdError": 0.000752674724334765,
                "TICVar": 0,
                "TIC*ITVar": 0,
                "TIC*ITMean": 0,
                "ShotNoise": 0.0005292657560073961
            },
            "Unsub": {
                "Average": 0.9049497768099624,
                "StdDev": 0.006894837598151804,
                "StdError": 5.8951772349807664e-05,
                "RelStdError": 6.514369510937778e-05,
                "TICVar": 0,
                "TIC*ITVar": 0,
                "TIC*ITMean": 0,
                "ShotNoise": 4.646006399185616e-05
            }
        },
        "104": {
            "13C": {
                "Average": 0.008759466693126947,
                "StdDev": 0.0016028456357388109,
                "StdError": 1.370454193950642e-05,
                "RelStdError": 0.001564540675776482,
                "TICVar": 0,
                "TIC*ITVar": 0,
                "TIC*ITMean": 0,
                "ShotNoise": 0.0011842240668362449
            },
            "13C-13C": {
                "Average": 0.011909259007591343,
                "StdDev": 0.0018936866327065706,
                "StdError": 1.6191270886948263e-05,
                "RelStdError": 0.0013595531742678054,
                "TICVar": 0,
                "TIC*ITVar": 0,
                "TIC*ITMean": 0,
                "ShotNoise": 0.0010142181466518683
            },
            "34S": {
                "Average": 0.9023473411860211,
                "StdDev": 0.005584421810249838,
                "StdError": 4.774754424257883e-05,
                "RelStdError": 5.291481679307742e-05,
                "TICVar": 0,
                "TIC*ITVar": 0,
                "TIC*ITMean": 0,
                "ShotNoise": 3.66240154972469e-05
            },
            "Unsub": {
                "Average": 0.07698393311326289,
                "StdDev": 0.005041172606646579,
                "StdError": 4.310269178243993e-05,
                "RelStdError": 0.0005598920455132493,
                "TICVar": 0,
                "TIC*ITVar": 0,
                "TIC*ITMean": 0,
                "ShotNoise": 0.0003854076218403846
            }
        },
        "133": {
            "18O": {
                "Average": 0.07102496455430334,
                "StdDev": 0.005999189121263573,
                "StdError": 5.1293859547173954e-05,
                "RelStdError": 0.000722194792620507,
                "TICVar": 0,
                "TIC*ITVar": 0,
                "TIC*ITMean": 0,
                "ShotNoise": 0.0005194820168590137
            },
            "34S": {
                "Average": 0.9289750354456985,
                "StdDev": 0.005999189121263586,
                "StdError": 5.129385954717406e-05,
                "RelStdError": 5.521554141932843e-05,
                "TICVar": 0,
                "TIC*ITVar": 0,
                "TIC*ITMean": 0,
                "ShotNoise": 3.9716952863387786e-05
            }
        },
        "56": {
            "13C": {
                "Average": 0.02376387137611623,
                "StdDev": 0.0012815192789781312,
                "StdError": 1.0957159138376142e-05,
                "RelStdError": 0.0004610847687632489,
                "TICVar": 0,
                "TIC*ITVar": 0,
                "TIC*ITMean": 0,
                "ShotNoise": 0.00033338974456815953
            },
            "13C-13C": {
                "Average": 0.006607749072825798,
                "StdDev": 0.0007199599540367376,
                "StdError": 6.155752721823177e-06,
                "RelStdError": 0.0009315960176421582,
                "TICVar": 0,
                "TIC*ITVar": 0,
                "TIC*ITMean": 0,
                "ShotNoise": 0.0006379217340813758
            },
            "13C-15N": {
                "Average": 0.0018996291925888003,
                "StdDev": 0.00035681944514613976,
                "StdError": 3.0508533958622155e-06,
                "RelStdError": 0.0016060257484801735,
                "TICVar": 0,
                "TIC*ITVar": 0,
                "TIC*ITMean": 0,
                "ShotNoise": 0.0011928254136189657
            },
            "15N": {
                "Average": 0.0020566076286101464,
                "StdDev": 0.00036380661816267046,
                "StdError": 3.1105946482377105e-06,
                "RelStdError": 0.0015124881406473473,
                "TICVar": 0,
                "TIC*ITVar": 0,
                "TIC*ITMean": 0,
                "ShotNoise": 0.0011463219304730134
            },
            "Unsub": {
                "Average": 0.9656721427298572,
                "StdDev": 0.0015742368860196514,
                "StdError": 1.3459933349869937e-05,
                "RelStdError": 1.3938409066891035e-05,
                "TICVar": 0,
                "TIC*ITVar": 0,
                "TIC*ITMean": 0,
                "ShotNoise": 9.806739556315326e-06
            }
        },
        "61": {
            "13C": {
                "Average": 0.016334977327282,
                "StdDev": 0.0011869749332124348,
                "StdError": 1.0148421549530665e-05,
                "RelStdError": 0.0006212693991672209,
                "TICVar": 0,
                "TIC*ITVar": 0,
                "TIC*ITMean": 0,
                "ShotNoise": 0.0004391996688493585
            },
            "13C-13C": {
                "Average": 0.0015718373073697214,
                "StdDev": 0.0003860868981724883,
                "StdError": 3.300973329572319e-06,
                "RelStdError": 0.0021000731526700407,
                "TICVar": 0,
                "TIC*ITVar": 0,
                "TIC*ITMean": 0,
                "ShotNoise": 0.0014278670598692304
            },
            "13C-33S": {
                "Average": 0.0021180387391102023,
                "StdDev": 0.0004819719744272013,
                "StdError": 4.1207734339504e-06,
                "RelStdError": 0.0019455609370400634,
                "TICVar": 0,
                "TIC*ITVar": 0,
                "TIC*ITMean": 0,
                "ShotNoise": 0.0012300559416768095
            },
            "33S": {
                "Average": 0.004938539124744114,
                "StdDev": 0.0006410903213003677,
                "StdError": 5.48120659487911e-06,
                "RelStdError": 0.0011098842099713272,
                "TICVar": 0,
                "TIC*ITVar": 0,
                "TIC*ITMean": 0,
                "ShotNoise": 0.0008035097800202184
            },
            "34S": {
                "Average": 0.8842182793893455,
                "StdDev": 0.0029419063535794506,
                "StdError": 2.5152768605285746e-05,
                "RelStdError": 2.844633411407942e-05,
                "TICVar": 0,
                "TIC*ITVar": 0,
                "TIC*ITMean": 0,
                "ShotNoise": 2.0484185647472268e-05
            },
            "Unsub": {
                "Average": 0.090818328112149,
                "StdDev": 0.0026233477954742514,
                "StdError": 2.242915040122412e-05,
                "RelStdError": 0.0002469672242097101,
                "TICVar": 0,
                "TIC*ITVar": 0,
                "TIC*ITMean": 0,
                "ShotNoise": 0.00017907484978198904
            }
        },
        "74High": {
            "18O": {
                "Average": 0.026398763559205618,
                "StdDev": 0.004982823499138888,
                "StdError": 4.260379920467568e-05,
                "RelStdError": 0.0016138558576475122,
                "TICVar": 0,
                "TIC*ITVar": 0,
                "TIC*ITMean": 0,
                "ShotNoise": 0.0012237756184526518
            },
            "Unsub": {
                "Average": 0.9736012364407998,
                "StdDev": 0.004982823499138891,
                "StdError": 4.26037992046757e-05,
                "RelStdError": 4.375898223016096e-05,
                "TICVar": 0,
                "TIC*ITVar": 0,
                "TIC*ITMean": 0,
                "ShotNoise": 3.317262004317284e-05
            }
        },
        "74Low": {
            "13C": {
                "Average": 0.013682448172942369,
                "StdDev": 0.0029472547706041238,
                "StdError": 2.5199417654175405e-05,
                "RelStdError": 0.0018417330974443843,
                "TICVar": 0,
                "TIC*ITVar": 0,
                "TIC*ITMean": 0,
                "ShotNoise": 0.0013577027582080104
            },
            "18O": {
                "Average": 0.06406654234990401,
                "StdDev": 0.00652622897110071,
                "StdError": 5.580011989117453e-05,
                "RelStdError": 0.0008709713033429864,
                "TICVar": 0,
                "TIC*ITVar": 0,
                "TIC*ITMean": 0,
                "ShotNoise": 0.0006109488412723259
            },
            "Unsub": {
                "Average": 0.9222510094771493,
                "StdDev": 0.007097410088406616,
                "StdError": 6.0683793903591096e-05,
                "RelStdError": 6.57996502904285e-05,
                "TICVar": 0,
                "TIC*ITVar": 0,
                "TIC*ITMean": 0,
                "ShotNoise": 4.6417731257514285e-05
            }
        },
        "87": {
            "13C": {
                "Average": 0.010488005526161324,
                "StdDev": 0.0020675817804239587,
                "StdError": 1.7678097373437166e-05,
                "RelStdError": 0.0016855537813496423,
                "TICVar": 0,
                "TIC*ITVar": 0,
                "TIC*ITMean": 0,
                "ShotNoise": 0.0012494907016964297
            },
            "13C-13C": {
                "Average": 0.010815403190589216,
                "StdDev": 0.002109020628973571,
                "StdError": 1.8032405003074405e-05,
                "RelStdError": 0.0016672892064500105,
                "TICVar": 0,
                "TIC*ITVar": 0,
                "TIC*ITMean": 0,
                "ShotNoise": 0.0012302684913429317
            },
            "34S": {
                "Average": 0.9077666311365533,
                "StdDev": 0.006320521616352078,
                "StdError": 5.404129483181808e-05,
                "RelStdError": 5.953214513311271e-05,
                "TICVar": 0,
                "TIC*ITVar": 0,
                "TIC*ITMean": 0,
                "ShotNoise": 4.10008049090052e-05
            },
            "Unsub": {
                "Average": 0.07092996014669432,
                "StdDev": 0.005725831203283455,
                "StdError": 4.895661323478786e-05,
                "RelStdError": 0.0006902106406592908,
                "TICVar": 0,
                "TIC*ITVar": 0,
                "TIC*ITMean": 0,
                "ShotNoise": 0.00046539868586742005
            }
        }
    },
    "20210906_23_Std04_MetA_M2_5e5.csv": {
        "102": {
            "13C": {
                "Average": 0.015171241929552937,
                "StdDev": 0.0027044082828154097,
                "StdError": 2.313404357030607e-05,
                "RelStdError": 0.0015248615556806811,
                "TICVar": 0,
                "TIC*ITVar": 0,
                "TIC*ITMean": 0,
                "ShotNoise": 0.0011579391264526996
            },
            "13C-13C": {
                "Average": 0.010638922077652335,
                "StdDev": 0.002367434883020164,
                "StdError": 2.025150643180054e-05,
                "RelStdError": 0.0019035299144017598,
                "TICVar": 0,
                "TIC*ITVar": 0,
                "TIC*ITMean": 0,
                "ShotNoise": 0.0013858989149536476
            },
            "18O": {
                "Average": 0.06847055138891253,
                "StdDev": 0.005999275178088128,
                "StdError": 5.131898694514516e-05,
                "RelStdError": 0.0007495045082031466,
                "TICVar": 0,
                "TIC*ITVar": 0,
                "TIC*ITMean": 0,
                "ShotNoise": 0.0005299789510712409
            },
            "Unsub": {
                "Average": 0.9057192846038816,
                "StdDev": 0.0068701960290764846,
                "StdError": 5.8769016232911505e-05,
                "RelStdError": 6.488656831306652e-05,
                "TICVar": 0,
                "TIC*ITVar": 0,
                "TIC*ITMean": 0,
                "ShotNoise": 4.635909411248269e-05
            }
        },
        "104": {
            "13C": {
                "Average": 0.008505378247605791,
                "StdDev": 0.001579856374913255,
                "StdError": 1.3514404035924805e-05,
                "RelStdError": 0.0015889245184044604,
                "TICVar": 0,
                "TIC*ITVar": 0,
                "TIC*ITMean": 0,
                "ShotNoise": 0.0012046007665818576
            },
            "13C-13C": {
                "Average": 0.011328985903246106,
                "StdDev": 0.0018381491640157793,
                "StdError": 1.572389166209531e-05,
                "RelStdError": 0.0013879346127167417,
                "TICVar": 0,
                "TIC*ITVar": 0,
                "TIC*ITMean": 0,
                "ShotNoise": 0.0010423171529337586
            },
            "34S": {
                "Average": 0.9031434402653542,
                "StdDev": 0.005445234364471729,
                "StdError": 4.6579612197857996e-05,
                "RelStdError": 5.1574988115035586e-05,
                "TICVar": 0,
                "TIC*ITVar": 0,
                "TIC*ITMean": 0,
                "ShotNoise": 3.6534048126394186e-05
            },
            "Unsub": {
                "Average": 0.07702219558379526,
                "StdDev": 0.004980279979748301,
                "StdError": 4.260230039078172e-05,
                "RelStdError": 0.0005531171900239213,
                "TICVar": 0,
                "TIC*ITVar": 0,
                "TIC*ITMean": 0,
                "ShotNoise": 0.0003861185395692486
            }
        },
        "133": {
            "18O": {
                "Average": 0.07107180761328286,
                "StdDev": 0.0059492459300040275,
                "StdError": 5.089102685778648e-05,
                "RelStdError": 0.0007160508303756056,
                "TICVar": 0,
                "TIC*ITVar": 0,
                "TIC*ITMean": 0,
                "ShotNoise": 0.0005201737324118003
            },
            "34S": {
                "Average": 0.9289281923867168,
                "StdDev": 0.00594924593000404,
                "StdError": 5.089102685778658e-05,
                "RelStdError": 5.478467256659644e-05,
                "TICVar": 0,
                "TIC*ITVar": 0,
                "TIC*ITMean": 0,
                "ShotNoise": 3.9794035930494764e-05
            }
        },
        "56": {
            "13C": {
                "Average": 0.022921646494992415,
                "StdDev": 0.0012474065048021586,
                "StdError": 1.0670562065404688e-05,
                "RelStdError": 0.0004655233675179414,
                "TICVar": 0,
                "TIC*ITVar": 0,
                "TIC*ITMean": 0,
                "ShotNoise": 0.000339855460212543
            },
            "13C-13C": {
                "Average": 0.006613260857526843,
                "StdDev": 0.0007275340355731543,
                "StdError": 6.2234700968702626e-06,
                "RelStdError": 0.0009410592188855,
                "TICVar": 0,
                "TIC*ITVar": 0,
                "TIC*ITMean": 0,
                "ShotNoise": 0.0006381532157720039
            },
            "13C-15N": {
                "Average": 0.0019036818834089126,
                "StdDev": 0.0003593110424443592,
                "StdError": 3.073617753657523e-06,
                "RelStdError": 0.0016145647970098936,
                "TICVar": 0,
                "TIC*ITVar": 0,
                "TIC*ITMean": 0,
                "ShotNoise": 0.0011925489041723098
            },
            "15N": {
                "Average": 0.0019821674908770074,
                "StdDev": 0.0003539285353985821,
                "StdError": 3.0275747233555835e-06,
                "RelStdError": 0.00152740610331372,
                "TICVar": 0,
                "TIC*ITVar": 0,
                "TIC*ITMean": 0,
                "ShotNoise": 0.0011685025085438928
            },
            "Unsub": {
                "Average": 0.9665792432731958,
                "StdDev": 0.0015476556292708876,
                "StdError": 1.3238952486164218e-05,
                "RelStdError": 1.3696706791811725e-05,
                "TICVar": 0,
                "TIC*ITVar": 0,
                "TIC*ITMean": 0,
                "ShotNoise": 9.679556137545197e-06
            }
        },
        "61": {
            "13C": {
                "Average": 0.015464244482973908,
                "StdDev": 0.0011504874732032866,
                "StdError": 9.838618177099778e-06,
                "RelStdError": 0.0006362171904312604,
                "TICVar": 0,
                "TIC*ITVar": 0,
                "TIC*ITMean": 0,
                "ShotNoise": 0.000451404612836342
            },
            "13C-13C": {
                "Average": 0.0014130754379824773,
                "StdDev": 0.00037713757631806536,
                "StdError": 3.2251655928935437e-06,
                "RelStdError": 0.0022823732592070836,
                "TICVar": 0,
                "TIC*ITVar": 0,
                "TIC*ITMean": 0,
                "ShotNoise": 0.0015053728344014631
            },
            "13C-33S": {
                "Average": 0.002006288008913252,
                "StdDev": 0.00046892925396528395,
                "StdError": 4.010140040022386e-06,
                "RelStdError": 0.0019987858284586783,
                "TICVar": 0,
                "TIC*ITVar": 0,
                "TIC*ITMean": 0,
                "ShotNoise": 0.0012633501687186633
            },
            "33S": {
                "Average": 0.004934987850057969,
                "StdDev": 0.0006385651868752226,
                "StdError": 5.46081482952711e-06,
                "RelStdError": 0.0011065508154114228,
                "TICVar": 0,
                "TIC*ITVar": 0,
                "TIC*ITMean": 0,
                "ShotNoise": 0.0008034627200783847
            },
            "34S": {
                "Average": 0.8852355329025203,
                "StdDev": 0.0029391768161160787,
                "StdError": 2.513494420607247e-05,
                "RelStdError": 2.839351028269248e-05,
                "TICVar": 0,
                "TIC*ITVar": 0,
                "TIC*ITMean": 0,
                "ShotNoise": 2.0372727869505534e-05
            },
            "Unsub": {
                "Average": 0.09094587131754747,
                "StdDev": 0.0026174170494264693,
                "StdError": 2.238335276075439e-05,
                "RelStdError": 0.000246117305123181,
                "TICVar": 0,
                "TIC*ITVar": 0,
                "TIC*ITMean": 0,
                "ShotNoise": 0.0001788596788688549
            }
        },
        "74High": {
            "18O": {
                "Average": 0.026288626757239995,
                "StdDev": 0.005028319146399077,
                "StdError": 4.3013236927783914e-05,
                "RelStdError": 0.0016361918530391813,
                "TICVar": 0,
                "TIC*ITVar": 0,
                "TIC*ITMean": 0,
                "ShotNoise": 0.0012278954644395182
            },
            "Unsub": {
                "Average": 0.9737113732427585,
                "StdDev": 0.005028319146399073,
                "StdError": 4.3013236927783887e-05,
                "RelStdError": 4.417452451493564e-05,
                "TICVar": 0,
                "TIC*ITVar": 0,
                "TIC*ITMean": 0,
                "ShotNoise": 3.314490090982403e-05
            }
        },
        "74Low": {
            "13C": {
                "Average": 0.013285226159058288,
                "StdDev": 0.0028835792138072218,
                "StdError": 2.4666707166418787e-05,
                "RelStdError": 0.0018567020893054383,
                "TICVar": 0,
                "TIC*ITVar": 0,
                "TIC*ITMean": 0,
                "ShotNoise": 0.0013786559926657858
            },
            "18O": {
                "Average": 0.0640547106485889,
                "StdDev": 0.006587036814575871,
                "StdError": 5.6346816283586046e-05,
                "RelStdError": 0.0008796670176641776,
                "TICVar": 0,
                "TIC*ITVar": 0,
                "TIC*ITMean": 0,
                "ShotNoise": 0.0006113785590750737
            },
            "Unsub": {
                "Average": 0.9226600631923547,
                "StdDev": 0.00713427060079515,
                "StdError": 6.102796237161718e-05,
                "RelStdError": 6.614349618695285e-05,
                "TICVar": 0,
                "TIC*ITVar": 0,
                "TIC*ITMean": 0,
                "ShotNoise": 4.630988425311575e-05
            }
        },
        "87": {
            "13C": {
                "Average": 0.010214183075473237,
                "StdDev": 0.0020223031088556736,
                "StdError": 1.7299180944649487e-05,
                "RelStdError": 0.0016936431251353885,
                "TICVar": 0,
                "TIC*ITVar": 0,
                "TIC*ITMean": 0,
                "ShotNoise": 0.0012668074063290282
            },
            "13C-13C": {
                "Average": 0.010272579745196152,
                "StdDev": 0.0020358640271623883,
                "StdError": 1.7415183723133178e-05,
                "RelStdError": 0.0016953077177402473,
                "TICVar": 0,
                "TIC*ITVar": 0,
                "TIC*ITMean": 0,
                "ShotNoise": 0.0012632430999293585
            },
            "34S": {
                "Average": 0.9085864232960044,
                "StdDev": 0.006401186140014501,
                "StdError": 5.4757012839263816e-05,
                "RelStdError": 6.0266157885813766e-05,
                "TICVar": 0,
                "TIC*ITVar": 0,
                "TIC*ITMean": 0,
                "ShotNoise": 4.081792904832525e-05
            },
            "Unsub": {
                "Average": 0.07092681388332198,
                "StdDev": 0.0057946464199896235,
                "StdError": 4.956855205864192e-05,
                "RelStdError": 0.0006988690079915979,
                "TICVar": 0,
                "TIC*ITVar": 0,
                "TIC*ITMean": 0,
                "ShotNoise": 0.0004656302654815312
            }
        }
    }
}